digitalhub_runtime_nefertem/__init__.py
digitalhub_runtime_nefertem/entities/__init__.py
digitalhub_runtime_nefertem/entities/functions/__init__.py
digitalhub_runtime_nefertem/entities/functions/spec.py
digitalhub_runtime_nefertem/entities/functions/status.py
digitalhub_runtime_nefertem/entities/runs/__init__.py
digitalhub_runtime_nefertem/entities/runs/spec.py
digitalhub_runtime_nefertem/entities/runs/status.py
digitalhub_runtime_nefertem/entities/tasks/__init__.py
digitalhub_runtime_nefertem/entities/tasks/spec.py
digitalhub_runtime_nefertem/entities/tasks/status.py
digitalhub_runtime_nefertem/runtimes/__init__.py
digitalhub_runtime_nefertem/runtimes/kind_registry.py
digitalhub_runtime_nefertem/runtimes/runtime.py
digitalhub_runtime_nefertem/utils/__init__.py
digitalhub_runtime_nefertem/utils/configurations.py
digitalhub_runtime_nefertem/utils/env.py
digitalhub_runtime_nefertem/utils/functions.py
digitalhub_runtime_nefertem/utils/inputs.py
digitalhub_runtime_nefertem/utils/outputs.py
digitalhub_runtime_nefertem-0.6.1.dist-info/LICENSE.txt
digitalhub_runtime_nefertem-0.6.1.dist-info/METADATA
digitalhub_runtime_nefertem-0.6.1.dist-info/WHEEL
digitalhub_runtime_nefertem-0.6.1.dist-info/top_level.txt
digitalhub_runtime_nefertem-0.6.1.dist-info/RECORD
