Metadata-Version: 2.1
Name: digitalhub-runtime-nefertem
Version: 0.6.1
Summary: Nefertem runtime for DHCore
Author-email: Fondazione Bruno Kessler <dslab@fbk.eu>, Matteo Martini <mmartini@fbk.eu>
License: Apache License
Project-URL: Homepage, https://github.com/scc-digitalhub/digitalhub-sdk
Keywords: data,dataops,kubernetes,validation,profiling,inference,nefertem,digitalhub
Classifier: License :: OSI Approved :: Apache Software License
Classifier: Programming Language :: Python :: 3.9
Classifier: Programming Language :: Python :: 3.10
Requires-Python: >=3.9
License-File: LICENSE.txt
Requires-Dist: digitalhub[data]<0.7,>=0.6.0
Provides-Extra: local
Requires-Dist: nefertem~=2.0; extra == "local"
Requires-Dist: nefertem-core~=2.0; extra == "local"
Requires-Dist: nefertem-inference~=2.0; extra == "local"
Requires-Dist: nefertem-profiling~=2.0; extra == "local"
Requires-Dist: nefertem-validation~=2.0; extra == "local"
Requires-Dist: nefertem-inference-frictionless; extra == "local"
Requires-Dist: nefertem-profiling-frictionless; extra == "local"
Requires-Dist: nefertem-validation-frictionless; extra == "local"
